{
    "version": "1.0.0.655",
    "last_update": "14 Feb 2026 16:32",
    "commits": [
        {
            "hash": "3d16541",
            "date": "2026-02-14 16:32:39 +0700",
            "author": "Admin Sancaka",
            "message": "Update System"
        },
        {
            "hash": "f47450e",
            "date": "2026-02-14 13:20:22 +0700",
            "author": "Admin Sancaka",
            "message": "Auto Bump Version"
        },
        {
            "hash": "7d2cfb3",
            "date": "2026-02-14 13:20:15 +0700",
            "author": "Admin Sancaka",
            "message": "Update System"
        },
        {
            "hash": "fb2974b",
            "date": "2026-02-14 13:08:52 +0700",
            "author": "Admin Sancaka",
            "message": "Auto Bump Version"
        },
        {
            "hash": "afb89bc",
            "date": "2026-02-14 13:08:47 +0700",
            "author": "Admin Sancaka",
            "message": "Update System"
        },
        {
            "hash": "425acf2",
            "date": "2026-02-14 13:06:21 +0700",
            "author": "Admin Sancaka",
            "message": "Auto Bump Version"
        },
        {
            "hash": "73ba0b0",
            "date": "2026-02-14 13:06:13 +0700",
            "author": "Admin Sancaka",
            "message": "Update System"
        },
        {
            "hash": "a8349e1",
            "date": "2026-02-14 13:04:41 +0700",
            "author": "Admin Sancaka",
            "message": "Auto Bump Version"
        },
        {
            "hash": "18ddc5a",
            "date": "2026-02-14 13:04:36 +0700",
            "author": "Admin Sancaka",
            "message": "Update System"
        },
        {
            "hash": "902a265",
            "date": "2026-02-14 13:03:40 +0700",
            "author": "Admin Sancaka",
            "message": "Auto Bump Version"
        },
        {
            "hash": "c896c95",
            "date": "2026-02-14 13:03:36 +0700",
            "author": "Admin Sancaka",
            "message": "Update System"
        },
        {
            "hash": "5771971",
            "date": "2026-02-14 13:02:38 +0700",
            "author": "Admin Sancaka",
            "message": "Auto Bump Version"
        },
        {
            "hash": "befbfcf",
            "date": "2026-02-14 13:02:32 +0700",
            "author": "Admin Sancaka",
            "message": "Update System"
        },
        {
            "hash": "c03566a",
            "date": "2026-02-14 13:01:43 +0700",
            "author": "Admin Sancaka",
            "message": "Auto Bump Version"
        },
        {
            "hash": "7fc0532",
            "date": "2026-02-14 13:01:37 +0700",
            "author": "Admin Sancaka",
            "message": "Update System"
        },
        {
            "hash": "4db637c",
            "date": "2026-02-14 12:52:18 +0700",
            "author": "Admin Sancaka",
            "message": "Auto Bump Version"
        },
        {
            "hash": "187dd12",
            "date": "2026-02-14 12:52:13 +0700",
            "author": "Admin Sancaka",
            "message": "Update System"
        },
        {
            "hash": "aa0e571",
            "date": "2026-02-14 12:50:13 +0700",
            "author": "Admin Sancaka",
            "message": "Auto Bump Version"
        },
        {
            "hash": "ba1a9fd",
            "date": "2026-02-14 12:50:08 +0700",
            "author": "Admin Sancaka",
            "message": "Update System"
        },
        {
            "hash": "d2468d6",
            "date": "2026-02-14 12:49:38 +0700",
            "author": "Admin Sancaka",
            "message": "Auto Bump Version"
        }
    ]
}