{
    "version": "1.0.0.736",
    "last_update": "16 Feb 2026 11:57",
    "commits": [
        {
            "hash": "cad831cf",
            "date": "2026-02-16 11:56:47 +0700",
            "author": "Admin Sancaka",
            "message": "Update System"
        },
        {
            "hash": "8926b4ca",
            "date": "2026-02-16 11:31:06 +0700",
            "author": "Admin Sancaka",
            "message": "Auto Bump Version"
        },
        {
            "hash": "90ad13d2",
            "date": "2026-02-16 11:31:00 +0700",
            "author": "Admin Sancaka",
            "message": "Update System"
        },
        {
            "hash": "1027bb81",
            "date": "2026-02-16 11:29:39 +0700",
            "author": "Admin Sancaka",
            "message": "Auto Bump Version"
        },
        {
            "hash": "11338dad",
            "date": "2026-02-16 11:29:35 +0700",
            "author": "Admin Sancaka",
            "message": "Update System"
        },
        {
            "hash": "541e1b5a",
            "date": "2026-02-16 11:29:02 +0700",
            "author": "Admin Sancaka",
            "message": "Auto Bump Version"
        },
        {
            "hash": "d56430b1",
            "date": "2026-02-16 11:28:57 +0700",
            "author": "Admin Sancaka",
            "message": "Update System"
        },
        {
            "hash": "77de190a",
            "date": "2026-02-16 11:23:00 +0700",
            "author": "Admin Sancaka",
            "message": "Auto Bump Version"
        },
        {
            "hash": "743089e5",
            "date": "2026-02-16 11:22:55 +0700",
            "author": "Admin Sancaka",
            "message": "Update System"
        },
        {
            "hash": "487a194f",
            "date": "2026-02-16 11:12:23 +0700",
            "author": "Admin Sancaka",
            "message": "Auto Bump Version"
        },
        {
            "hash": "ef7a15bd",
            "date": "2026-02-16 11:12:18 +0700",
            "author": "Admin Sancaka",
            "message": "Update System"
        },
        {
            "hash": "99380ed8",
            "date": "2026-02-16 11:11:09 +0700",
            "author": "Admin Sancaka",
            "message": "Auto Bump Version"
        },
        {
            "hash": "5f84f498",
            "date": "2026-02-16 11:11:05 +0700",
            "author": "Admin Sancaka",
            "message": "Update System"
        },
        {
            "hash": "b0f7b6dd",
            "date": "2026-02-16 11:02:50 +0700",
            "author": "Admin Sancaka",
            "message": "Auto Bump Version"
        },
        {
            "hash": "b836e059",
            "date": "2026-02-16 11:02:46 +0700",
            "author": "Admin Sancaka",
            "message": "Update System"
        },
        {
            "hash": "448f1ee1",
            "date": "2026-02-16 10:55:06 +0700",
            "author": "Admin Sancaka",
            "message": "Auto Bump Version"
        },
        {
            "hash": "1fb9baaa",
            "date": "2026-02-16 10:55:01 +0700",
            "author": "Admin Sancaka",
            "message": "Update System"
        },
        {
            "hash": "e928a130",
            "date": "2026-02-16 10:53:11 +0700",
            "author": "Admin Sancaka",
            "message": "Auto Bump Version"
        },
        {
            "hash": "4b543224",
            "date": "2026-02-16 10:53:07 +0700",
            "author": "Admin Sancaka",
            "message": "Update System"
        },
        {
            "hash": "ae213a2a",
            "date": "2026-02-16 10:39:35 +0700",
            "author": "Admin Sancaka",
            "message": "Auto Bump Version"
        }
    ]
}